vaderSentiment/__init__.py
vaderSentiment/emoji_utf8_lexicon.txt
vaderSentiment/vaderSentiment.py
vaderSentiment/vader_lexicon.txt
vaderSentiment-3.2.1.dist-info/LICENSE.txt
vaderSentiment-3.2.1.dist-info/METADATA
vaderSentiment-3.2.1.dist-info/RECORD
vaderSentiment-3.2.1.dist-info/WHEEL
vaderSentiment-3.2.1.dist-info/top_level.txt
