Metadata-Version: 2.1
Name: vaderSentiment
Version: 3.2.1
Summary: VADER Sentiment Analysis. VADER (Valence Aware Dictionary and sEntiment Reasoner) is a lexicon and rule-based sentiment analysis tool that is specifically attuned to sentiments expressed in social media, and works well on texts from other domains.
Home-page: https://github.com/cjhutto/vaderSentiment
Author: C.J. Hutto
Author-email: cjhutto@gatech.edu
License: MIT License: http://opensource.org/licenses/MIT
Download-URL: https://github.com/cjhutto/vaderSentiment/archive/master.zip
Keywords: vader,sentiment,analysis,opinion,mining,nlp,text,data,text analysis,opinion analysis,sentiment analysis,text mining,twitter sentiment,opinion mining,social media,twitter,social,media
Platform: UNKNOWN
Classifier: Development Status :: 4 - Beta
Classifier: Intended Audience :: Science/Research
Classifier: License :: OSI Approved :: MIT License
Classifier: Natural Language :: English
Classifier: Programming Language :: Python :: 3.5
Classifier: Topic :: Scientific/Engineering :: Artificial Intelligence
Classifier: Topic :: Scientific/Engineering :: Information Analysis
Classifier: Topic :: Text Processing :: Linguistic
Classifier: Topic :: Text Processing :: General
